disaster_id_scan/__about__.py
disaster_id_scan/__init__.py
disaster_id_scan/__main__.py
disaster_id_scan/id_scanner.py
disaster_id_scan/mrz.py
disaster_id_scan/store.py
disaster_id_scan/ui.py
disaster_id_scan/cli/__init__.py
disaster_id_scan-0.3.0.dist-info/METADATA
disaster_id_scan-0.3.0.dist-info/WHEEL
disaster_id_scan-0.3.0.dist-info/entry_points.txt
disaster_id_scan-0.3.0.dist-info/licenses/LICENSE.txt
disaster_id_scan-0.3.0.dist-info/RECORD
