Metadata-Version: 2.1
Name: disaster-id-scan
Version: 0.3.0
Project-URL: Documentation, https://github.com/anjomro/disaster-id-scan#readme
Project-URL: Issues, https://github.com/anjomro/disaster-id-scan/issues
Project-URL: Source, https://github.com/anjomro/disaster-id-scan
Author-email: anjomro <py@anjomro.de>
License-Expression: EUPL-1.2
License-File: LICENSE.txt
Classifier: Development Status :: 4 - Beta
Classifier: Programming Language :: Python
Classifier: Programming Language :: Python :: 3.7
Classifier: Programming Language :: Python :: 3.8
Classifier: Programming Language :: Python :: 3.9
Classifier: Programming Language :: Python :: 3.10
Classifier: Programming Language :: Python :: 3.11
Classifier: Programming Language :: Python :: Implementation :: CPython
Classifier: Programming Language :: Python :: Implementation :: PyPy
Requires-Python: >=3.7
Requires-Dist: click
Requires-Dist: easyocr
Requires-Dist: jsonpickle
Requires-Dist: opencv-python
Requires-Dist: sv-ttk
Requires-Dist: tkcalendar
